LICENSE
README.md
pyproject.toml
setup.py
metrograph/Action.py
metrograph/__init__.py
metrograph.egg-info/PKG-INFO
metrograph.egg-info/SOURCES.txt
metrograph.egg-info/dependency_links.txt
metrograph.egg-info/requires.txt
metrograph.egg-info/top_level.txt
metrograph/errors/APIError.py
metrograph/errors/BuildError.py
metrograph/errors/ContainerError.py
metrograph/errors/ImageNotFound.py
metrograph/errors/__init__.py
tests/__init__.py