Metadata-Version: 2.1
Name: metrograph
Version: 0.0.1
Summary: Metrograph's core official package
Home-page: https://github.com/metrograph/metrograph-core
Author: Hamza EL GARRAB
Author-email: hamza.elgarrab@gmail.com
License: MIT
Platform: UNKNOWN
Classifier: Programming Language :: Python :: 3.7
Classifier: Development Status :: 1 - Planning
Classifier: License :: OSI Approved :: MIT License
Classifier: Operating System :: POSIX :: Linux
License-File: LICENSE
